odoo/addons/sm_partago_tariffs/__init__.py
odoo/addons/sm_partago_tariffs/__manifest__.py
odoo/addons/sm_partago_tariffs/email_tmpl/abouttoexpire_tariff_email.xml
odoo/addons/sm_partago_tariffs/email_tmpl/notification_tariff_created.xml
odoo/addons/sm_partago_tariffs/models/__init__.py
odoo/addons/sm_partago_tariffs/models/models_carsharing_user_request.py
odoo/addons/sm_partago_tariffs/models/models_cs_carconfig.py
odoo/addons/sm_partago_tariffs/models/models_sm_company.py
odoo/addons/sm_partago_tariffs/models/models_sm_member.py
odoo/addons/sm_partago_tariffs/models/models_smp_carconfig_price_group.py
odoo/addons/sm_partago_tariffs/models/models_smp_carconfig_tariff_group.py
odoo/addons/sm_partago_tariffs/models/models_smp_carsharing_send_email_tariff_wizard.py
odoo/addons/sm_partago_tariffs/models/models_smp_carsharing_tariff.py
odoo/addons/sm_partago_tariffs/models/models_smp_carsharing_tariff_history.py
odoo/addons/sm_partago_tariffs/models/models_smp_carsharing_tariff_model.py
odoo/addons/sm_partago_tariffs/models/models_smp_reservation_compute.py
odoo/addons/sm_partago_tariffs/models/models_smp_tariffmodel_price_group.py
odoo/addons/sm_partago_tariffs/models/models_smp_tariffs_cron.py
odoo/addons/sm_partago_tariffs/models/res_config_settings.py
odoo/addons/sm_partago_tariffs/security/ir.model.access.csv
odoo/addons/sm_partago_tariffs/views/views.xml
odoo/addons/sm_partago_tariffs/views/views_carconfig_price_group.xml
odoo/addons/sm_partago_tariffs/views/views_carconfig_tariff_group.xml
odoo/addons/sm_partago_tariffs/views/views_carsharing_user_request.xml
odoo/addons/sm_partago_tariffs/views/views_cron.xml
odoo/addons/sm_partago_tariffs/views/views_cs_carconfig.xml
odoo/addons/sm_partago_tariffs/views/views_members.xml
odoo/addons/sm_partago_tariffs/views/views_res_config_settings.xml
odoo/addons/sm_partago_tariffs/views/views_reservation_compute.xml
odoo/addons/sm_partago_tariffs/views/views_tariff.xml
odoo12_addon_sm_partago_tariffs-12.0.0.0.9.dist-info/METADATA
odoo12_addon_sm_partago_tariffs-12.0.0.0.9.dist-info/WHEEL
odoo12_addon_sm_partago_tariffs-12.0.0.0.9.dist-info/top_level.txt
odoo12_addon_sm_partago_tariffs-12.0.0.0.9.dist-info/RECORD
